{"cameraMode":{"drawMode":0,"name":"Shaded","section":"Shading Mode"},"sceneLighting":true,"audioPlay":false,"sceneViewState":{"showFog":false,"showMaterialUpdate":false,"showSkybox":false,"showFlares":false,"showImageEffects":false,"showParticleSystems":false,"showVisualEffectGraphs":true,"m_FxEnabled":true},"in2DMode":false,"pivot":{"x":2.074248790740967,"y":2.4310495853424074,"z":-4.664621353149414},"rotation":{"x":0.12719255685806275,"y":-0.7408077120780945,"z":0.14659376442432404,"w":0.6431394219398499},"size":0.9679183959960938,"orthographic":false}